odoo/addons/product_disable_translation/LICENSE
odoo/addons/product_disable_translation/README.rst
odoo/addons/product_disable_translation/__init__.py
odoo/addons/product_disable_translation/__manifest__.py
odoo/addons/product_disable_translation/images/screen.png
odoo/addons/product_disable_translation/models/__init__.py
odoo/addons/product_disable_translation/models/product_template.py
odoo/addons/product_disable_translation/static/description/icon.png
odoo/addons/product_disable_translation/static/description/index.html
odoo_addon_product_disable_translation-16.0.1.0.0.dist-info/METADATA
odoo_addon_product_disable_translation-16.0.1.0.0.dist-info/WHEEL
odoo_addon_product_disable_translation-16.0.1.0.0.dist-info/top_level.txt
odoo_addon_product_disable_translation-16.0.1.0.0.dist-info/RECORD
